qdk_chemistry/__init__.py
qdk_chemistry/_core.cpython-310-x86_64-linux-gnu.so
qdk_chemistry/constants.py
qdk_chemistry/definitions.py
qdk_chemistry/py.typed
qdk_chemistry/_core/__init__.pyi
qdk_chemistry/_core/_algorithms.pyi
qdk_chemistry/_core/constants.pyi
qdk_chemistry/_core/data.pyi
qdk_chemistry/_core/utils.pyi
qdk_chemistry/algorithms/__init__.py
qdk_chemistry/algorithms/active_space_selector.py
qdk_chemistry/algorithms/base.py
qdk_chemistry/algorithms/dynamical_correlation_calculator.py
qdk_chemistry/algorithms/hamiltonian_constructor.py
qdk_chemistry/algorithms/multi_configuration_calculator.py
qdk_chemistry/algorithms/multi_configuration_scf.py
qdk_chemistry/algorithms/orbital_localizer.py
qdk_chemistry/algorithms/projected_multi_configuration_calculator.py
qdk_chemistry/algorithms/qubit_hamiltonian_solver.py
qdk_chemistry/algorithms/registry.py
qdk_chemistry/algorithms/registry.pyi
qdk_chemistry/algorithms/scf_solver.py
qdk_chemistry/algorithms/stability_checker.py
qdk_chemistry/algorithms/circuit_executor/__init__.py
qdk_chemistry/algorithms/circuit_executor/base.py
qdk_chemistry/algorithms/circuit_executor/qdk.py
qdk_chemistry/algorithms/energy_estimator/__init__.py
qdk_chemistry/algorithms/energy_estimator/energy_estimator.py
qdk_chemistry/algorithms/energy_estimator/qsharp.py
qdk_chemistry/algorithms/phase_estimation/__init__.py
qdk_chemistry/algorithms/phase_estimation/base.py
qdk_chemistry/algorithms/phase_estimation/iterative_phase_estimation.py
qdk_chemistry/algorithms/qubit_mapper/__init__.py
qdk_chemistry/algorithms/qubit_mapper/qdk_qubit_mapper.py
qdk_chemistry/algorithms/qubit_mapper/qubit_mapper.py
qdk_chemistry/algorithms/state_preparation/__init__.py
qdk_chemistry/algorithms/state_preparation/sparse_isometry.py
qdk_chemistry/algorithms/state_preparation/state_preparation.py
qdk_chemistry/algorithms/time_evolution/__init__.py
qdk_chemistry/algorithms/time_evolution/builder/__init__.py
qdk_chemistry-1.0.1.dist-info/METADATA
qdk_chemistry-1.0.1.dist-info/WHEEL
qdk_chemistry-1.0.1.dist-info/RECORD
qdk_chemistry-1.0.1.dist-info/licenses/LICENSE.txt
