Metadata-Version: 2.2
Name: qdk-chemistry
Version: 1.0.1
Summary: Quantum Development Kit - Chemistry Library
Author-Email: QDK/Chemistry Development Team <qdk-chemistry@microsoft.com>
License: MIT License
Classifier: Development Status :: 4 - Beta
Classifier: Intended Audience :: Science/Research
Classifier: License :: OSI Approved :: MIT License
Classifier: Programming Language :: Python :: 3
Classifier: Programming Language :: Python :: 3.10
Classifier: Programming Language :: Python :: 3.11
Classifier: Programming Language :: Python :: 3.12
Classifier: Programming Language :: Python :: 3.13
Classifier: Programming Language :: C++
Classifier: Topic :: Scientific/Engineering
Classifier: Topic :: Scientific/Engineering :: Quantum Computing
Classifier: Topic :: Scientific/Engineering :: Physics
Classifier: Topic :: Scientific/Engineering :: Chemistry
Classifier: Topic :: Software Development :: Libraries
Classifier: Topic :: Software Development :: Libraries :: Python Modules
Classifier: Topic :: Education
Project-URL: Documentation, https://microsoft.github.io/qdk-chemistry
Project-URL: Homepage, https://github.com/microsoft/qdk-chemistry
Project-URL: Issues, https://github.com/microsoft/qdk-chemistry/issues
Project-URL: Repository, https://github.com/microsoft/qdk-chemistry
Project-URL: Source, https://github.com/microsoft/qdk-chemistry
Project-URL: Changelog, https://github.com/microsoft/qdk-chemistry/releases
Requires-Python: >=3.10
Requires-Dist: numpy<2.4.0,>=1.20.0
Requires-Dist: scipy>=1.7.0
Requires-Dist: matplotlib==3.10.0
Requires-Dist: qiskit[qasm3-import]>=2.2.0
Requires-Dist: qiskit-aer
Requires-Dist: qiskit-nature
Requires-Dist: pylatexenc==2.10
Requires-Dist: ruamel-yaml>=0.18.10
Requires-Dist: pydantic-settings>=2.9.1
Requires-Dist: qdk[jupyter]>=1.25.0
Requires-Dist: pybind11-stubgen>=2.5.1
Requires-Dist: h5py>=3.0.0
Provides-Extra: all
Requires-Dist: qdk-chemistry[coverage,dev,docs,plugins]; extra == "all"
Provides-Extra: coverage
Requires-Dist: coverage; extra == "coverage"
Requires-Dist: pytest; extra == "coverage"
Requires-Dist: pytest-cov; extra == "coverage"
Requires-Dist: gcovr; extra == "coverage"
Provides-Extra: dev
Requires-Dist: coverage; extra == "dev"
Requires-Dist: mypy; extra == "dev"
Requires-Dist: nbclient; extra == "dev"
Requires-Dist: nbformat; extra == "dev"
Requires-Dist: pytest; extra == "dev"
Requires-Dist: pytest-env; extra == "dev"
Requires-Dist: ruff; extra == "dev"
Provides-Extra: docs
Requires-Dist: sphinx; extra == "docs"
Requires-Dist: sphinx-rtd-theme; extra == "docs"
Requires-Dist: myst-parser; extra == "docs"
Requires-Dist: breathe; extra == "docs"
Requires-Dist: sphinx-autodoc-typehints; extra == "docs"
Requires-Dist: sphinx-inline-tabs; extra == "docs"
Requires-Dist: sphinxcontrib-napoleon; extra == "docs"
Requires-Dist: sphinxcontrib-bibtex; extra == "docs"
Requires-Dist: sphinx_copybutton; extra == "docs"
Provides-Extra: plugins
Requires-Dist: pyscf>=2.9.0; extra == "plugins"
